marco_sven/__init__.py
pygments_style_marcosven-0.1.22.dist-info/METADATA
pygments_style_marcosven-0.1.22.dist-info/WHEEL
pygments_style_marcosven-0.1.22.dist-info/entry_points.txt
pygments_style_marcosven-0.1.22.dist-info/top_level.txt
pygments_style_marcosven-0.1.22.dist-info/RECORD
