Metadata-Version: 2.1
Name: pygments-style-marcosven
Version: 0.1.22
Summary: Custom Pygments style for Aider
Home-page: https://github.com/marcoSven/pygments-style-marcosven
Author: marcoSven
Author-email: me@marcoSven.com
Classifier: Programming Language :: Python :: 3
Classifier: License :: OSI Approved :: MIT License
Requires-Python: >=3.7
Requires-Dist: pygments>=2.0
